{
  "build": {
    "beforeDevCommand": "npm run dev",
    "beforeBuildCommand": "npm run build",
    "devPath": "http://localhost:1420",
    "distDir": "../dist"
  },
  "package": {
    "productName": "toolkit",
    "version": "0.0.0"
  },
  "tauri": {
    "allowlist": {
      "all": true
    },
    "bundle": {
      "active": true,
      "category": "Utility",
      "copyright": "© 2022 hafiz haziq",
      "deb": {
        "depends": []
      },
      "externalBin": [],
      "icon": [
        "icons/32x32.png",
        "icons/128x128.png",
        "icons/128x128@2x.png",
        "icons/icon.icns",
        "icons/icon.ico"
      ],
      "identifier": "hafizhaziq.dev.toolkit",
      "longDescription": "",
      "macOS": {
        "entitlements": null,
        "exceptionDomain": "",
        "frameworks": [],
        "providerShortName": null,
        "signingIdentity": null
      },
      "resources": [],
      "shortDescription": "",
      "targets": "all",
      "windows": {
        "certificateThumbprint": null,
        "digestAlgorithm": "sha256",
        "timestampUrl": ""
      }
    },
    "security": {
      "csp": null
    },
    "updater": {
      "active": false
    },
    "windows": [
      {
        "fullscreen": false,
        "height": 600,
        "minHeight": 600,
        "resizable": true,
        "title": "toolkit",
        "width": 800, 
        "maxWidth": 800
      }
    ]
  }
}
